chowlk/__init__.py
chowlk/anonymousClass.py
chowlk/associations.py
chowlk/converter.py
chowlk/finding.py
chowlk/geometry.py
chowlk/transformations.py
chowlk/utils.py
chowlk/writer.py
chowlk_unofficial_fork-0.0.2.dist-info/LICENSE
chowlk_unofficial_fork-0.0.2.dist-info/METADATA
chowlk_unofficial_fork-0.0.2.dist-info/WHEEL
chowlk_unofficial_fork-0.0.2.dist-info/entry_points.txt
chowlk_unofficial_fork-0.0.2.dist-info/top_level.txt
chowlk_unofficial_fork-0.0.2.dist-info/RECORD
