Metadata-Version: 2.1
Name: chowlk-unofficial-fork
Version: 0.0.2
Summary: Temporary unofficial fork from Chowlk
Home-page: https://github.com/pablo-de-andres/Chowlk
Author: Serge Chávez-Feria, Pablo de Andres
Author-email: chavezferia.justinian@gmail.com, pablo.de.andres@iwm.fraunhofer.de
License: Apache-2.0
Project-URL: Chowlk Visual Notation, https://chowlk.linkeddata.es/chowlk_spec
Classifier: License :: OSI Approved :: Apache Software License
Classifier: Operating System :: OS Independent
Classifier: Programming Language :: Python :: 3
Classifier: Programming Language :: Python :: 3 :: Only
Requires-Python: >=3.7
License-File: LICENSE
Requires-Dist: beautifulsoup4 (>=4.9.1)
Requires-Dist: rdflib (<7.0.0,>=5.0.0)
